[
    {
        "name": "Araç Akdene Göce Çorbası",
        "CityName": "Kastamonu",
        "code": [
            {
                "uri": "https://ci.turkpatent.gov.tr/Pictures/GeographicalSigns/40c6a9f1-7a8a-4b77-af16-87ec5687d3f2.jpeg"
            }
        ],
        "jsonURL": "http://ruzgarerik.com/turkeyfoodpassport/arac_akdene_goce_corbasi.json"
    },
    {
        "name": "Araç Kül Çöreği",
        "CityName": "Kastamonu",
        "code": [
            {
                "uri": "https://ci.turkpatent.gov.tr/Pictures/GeographicalSigns/d4296479-95f0-4033-aa0d-8a32a6c3e0dd.jpeg"
            }
        ],
        "jsonURL": "http://ruzgarerik.com/turkeyfoodpassport/arac_kul_coregi.json"
    },
    {
        "name": "Azdavay Yöresel Giysileri",
        "CityName": "Kastamonu",
        "code": [
            {
                "uri": "https://ci.turkpatent.gov.tr/Pictures/GeographicalSigns/ec4572f1-cd3b-44e0-8257-f63e92d07be9.jpeg"
            }
        ],
        "jsonURL": "http://ruzgarerik.com/turkeyfoodpassport/azdavay_yoresel_giysileri.json"
    },
    {
        "name": "Cide Ceviz Helvası",
        "CityName": "Kastamonu",
        "code": [
            {
                "uri": "https://ci.turkpatent.gov.tr/Pictures/GeographicalSigns/d6e62382-261f-4be2-b114-deb348b16505.jpeg"
            }
        ],
        "jsonURL": "http://ruzgarerik.com/turkeyfoodpassport/cide_ceviz_helvasi.json"
    },
    {
        "name": "Daday Etli Ekmeği",
        "CityName": "Kastamonu",
        "code": [
            {
                "uri": "https://ci.turkpatent.gov.tr/Pictures/GeographicalSigns/378.jpg"
            }
        ],
        "jsonURL": "http://ruzgarerik.com/turkeyfoodpassport/daday_etli_ekmegi.json"
    },
    {
        "name": "Devrekani Cırık Tatlısı",
        "CityName": "Kastamonu",
        "code": [
            {
                "uri": "https://ci.turkpatent.gov.tr/Pictures/GeographicalSigns/84113439-f2a6-4e24-b1e6-7efba91d3d9e.jpeg"
            }
        ],
        "jsonURL": "http://ruzgarerik.com/turkeyfoodpassport/devrekani_cirik_tatlisi.json"
    },
    {
        "name": "Devrekani Hindi Banduması",
        "CityName": "Kastamonu",
        "code": [
            {
                "uri": "https://ci.turkpatent.gov.tr/Pictures/GeographicalSigns/672de1c9-11bc-4e5d-abd1-3eb4d7174fa1.jpeg"
            }
        ],
        "jsonURL": "http://ruzgarerik.com/turkeyfoodpassport/devrekani_hindi_bandumasi.json"
    },
    {
        "name": "Evrenye Bıçağı",
        "CityName": "Kastamonu",
        "code": [
            {
                "uri": "https://ci.turkpatent.gov.tr/Pictures/GeographicalSigns/71cf1fb9-9c71-4fdc-8cef-06830e69ff4a.jpeg"
            }
        ],
        "jsonURL": "http://ruzgarerik.com/turkeyfoodpassport/evrenye_bicagi.json"
    },
    {
        "name": "Kastamonu Pastırması",
        "CityName": "Kastamonu",
        "code": [
            {
                "uri": "https://ci.turkpatent.gov.tr/Pictures/GeographicalSigns/26db2c35-7036-479d-9cf2-104cf9596027.jpeg"
            }
        ],
        "jsonURL": "http://ruzgarerik.com/turkeyfoodpassport/kastamonu_pastirmasi.json"
    },
    {
        "name": "Kastamonu Simidi",
        "CityName": "Kastamonu",
        "code": [
            {
                "uri": "https://ci.turkpatent.gov.tr/Pictures/GeographicalSigns/60d1ed3f-2bb7-4db4-be7f-c64173fad70d.jpeg"
            }
        ],
        "jsonURL": "http://ruzgarerik.com/turkeyfoodpassport/kastamonu_simidi.json"
    },
    {
        "name": "Kastamonu Siyez Bulguru",
        "CityName": "Kastamonu",
        "code": [
            {
                "uri": "https://ci.turkpatent.gov.tr/Pictures/GeographicalSigns/8d376d51-5ba3-4bfe-862b-dd367444a228.jpeg"
            }
        ],
        "jsonURL": "http://ruzgarerik.com/turkeyfoodpassport/kastamonu_siyez_bulguru.json"
    },
    {
        "name": "Kastamonu Siyez Buğdayı",
        "CityName": "Kastamonu",
        "code": [
            {
                "uri": "https://ci.turkpatent.gov.tr/Pictures/GeographicalSigns/4df60c3a-aff1-4ce8-941a-5954cb1183f1.jpeg"
            }
        ],
        "jsonURL": "http://ruzgarerik.com/turkeyfoodpassport/kastamonu_siyez_bugdayi.json"
    },
    {
        "name": "Kastamonu Siyez Unu",
        "CityName": "Kastamonu",
        "code": [
            {
                "uri": "https://ci.turkpatent.gov.tr/Pictures/GeographicalSigns/30ea64c0-eae3-4f0a-938b-030de13a71fc.jpeg"
            }
        ],
        "jsonURL": "http://ruzgarerik.com/turkeyfoodpassport/kastamonu_siyez_unu.json"
    },
    {
        "name": "Kastamonu Taş Baskı Dokuması",
        "CityName": "Kastamonu",
        "code": [
            {
                "uri": "https://ci.turkpatent.gov.tr/Pictures/GeographicalSigns/803d6704-589f-41ad-a9ba-10c6e7123bf7.jpeg"
            }
        ],
        "jsonURL": "http://ruzgarerik.com/turkeyfoodpassport/kastamonu_tas_baski_dokumasi.json"
    },
    {
        "name": "Kastamonu Tiridi / Kastamonu Simit Tiridi",
        "CityName": "Kastamonu",
        "code": [
            {
                "uri": "https://ci.turkpatent.gov.tr/Pictures/GeographicalSigns/874e94d3-b602-49ce-8e06-f822842a01b2.jpeg"
            }
        ],
        "jsonURL": "http://ruzgarerik.com/turkeyfoodpassport/kastamonu_tiridi__kastamonu_simit_tiridi.json"
    },
    {
        "name": "Kastamonu Çekme Helvası",
        "CityName": "Kastamonu",
        "code": [
            {
                "uri": "https://ci.turkpatent.gov.tr/Pictures/GeographicalSigns/388.jpg"
            }
        ],
        "jsonURL": "http://ruzgarerik.com/turkeyfoodpassport/kastamonu_cekme_helvasi.json"
    },
    {
        "name": "Kastamonu Örme Fanilası/Kastamonu Fanilası",
        "CityName": "Kastamonu",
        "code": [
            {
                "uri": "https://ci.turkpatent.gov.tr/Pictures/GeographicalSigns/137225cf-b104-429a-a91b-c06b32cf64d3.png"
            }
        ],
        "jsonURL": "http://ruzgarerik.com/turkeyfoodpassport/kastamonu_orme_fanilasikastamonu_fanilasi.json"
    },
    {
        "name": "Kastamonu Üryani Eriği",
        "CityName": "Kastamonu",
        "code": [
            {
                "uri": "https://ci.turkpatent.gov.tr/Pictures/GeographicalSigns/6294450d-9be8-4dad-baac-43d55769fe7a.jpeg"
            }
        ],
        "jsonURL": "http://ruzgarerik.com/turkeyfoodpassport/kastamonu_uryani_erigi.json"
    },
    {
        "name": "Pınarbaşı Kara Çorba",
        "CityName": "Kastamonu",
        "code": [
            {
                "uri": "https://ci.turkpatent.gov.tr/Pictures/GeographicalSigns/319.jpg"
            }
        ],
        "jsonURL": "http://ruzgarerik.com/turkeyfoodpassport/pinarbasi_kara_corba.json"
    },
    {
        "name": "Taşköprü Kuyu Kebabı",
        "CityName": "Kastamonu",
        "code": [
            {
                "uri": "https://ci.turkpatent.gov.tr/Pictures/GeographicalSigns/ed6a7e55-00fb-4dce-b14c-794fc6db1441.jpeg"
            }
        ],
        "jsonURL": "http://ruzgarerik.com/turkeyfoodpassport/taskopru_kuyu_kebabi.json"
    },
    {
        "name": "Taşköprü Sarımsağı",
        "CityName": "Kastamonu",
        "code": [
            {
                "uri": "https://ci.turkpatent.gov.tr/Pictures/GeographicalSigns/135.jpg"
            }
        ],
        "jsonURL": "http://ruzgarerik.com/turkeyfoodpassport/taskopru_sarimsagi.json"
    },
    {
        "name": "Tosya Bıçkısı",
        "CityName": "Kastamonu",
        "code": [
            {
                "uri": "https://ci.turkpatent.gov.tr/Pictures/GeographicalSigns/377.jpeg"
            }
        ],
        "jsonURL": "http://ruzgarerik.com/turkeyfoodpassport/tosya_bickisi.json"
    },
    {
        "name": "Tosya Kıl Telası",
        "CityName": "Kastamonu",
        "code": [
            {
                "uri": "https://ci.turkpatent.gov.tr/Pictures/GeographicalSigns/72e94f4e-3e5b-44c6-ba67-70aa102af671.jpeg"
            }
        ],
        "jsonURL": "http://ruzgarerik.com/turkeyfoodpassport/tosya_kil_telasi.json"
    },
    {
        "name": "Tosya Kıstısı",
        "CityName": "Kastamonu",
        "code": [
            {
                "uri": "https://ci.turkpatent.gov.tr/Pictures/GeographicalSigns/34b0c15b-681b-44a9-b7e1-9f6c8c22624b.jpeg"
            }
        ],
        "jsonURL": "http://ruzgarerik.com/turkeyfoodpassport/tosya_kistisi.json"
    },
    {
        "name": "Tosya Pirinci",
        "CityName": "Kastamonu",
        "code": [
            {
                "uri": "https://ci.turkpatent.gov.tr/Pictures/GeographicalSigns/230.jpg"
            }
        ],
        "jsonURL": "http://ruzgarerik.com/turkeyfoodpassport/tosya_pirinci.json"
    },
    {
        "name": "Çatalzeytin Fındık Şekeri",
        "CityName": "Kastamonu",
        "code": [
            {
                "uri": "https://ci.turkpatent.gov.tr/Pictures/GeographicalSigns/59ca8bb2-98b0-4896-86db-5829e72306cf.jpeg"
            }
        ],
        "jsonURL": "http://ruzgarerik.com/turkeyfoodpassport/catalzeytin_findik_sekeri.json"
    },
    {
        "name": "İhsangazi Ekşili Pilavı",
        "CityName": "Kastamonu",
        "code": [
            {
                "uri": "https://ci.turkpatent.gov.tr/Pictures/GeographicalSigns/93e7db05-7337-4adb-a901-d47923918b8f.jpeg"
            }
        ],
        "jsonURL": "http://ruzgarerik.com/turkeyfoodpassport/ihsangazi_eksili_pilavi.json"
    }
]